setup.py
start.py
gbridge.egg-info/PKG-INFO
gbridge.egg-info/SOURCES.txt
gbridge.egg-info/dependency_links.txt
gbridge.egg-info/entry_points.txt
gbridge.egg-info/top_level.txt