Metadata-Version: 1.0
Name: gbridge
Version: 0.1.0
Summary: MacOS and OSX bridge interface listing
Home-page: https://www.github.com/illberoy/gbridge
Author: Roy Sommer
Author-email: UNKNOWN
License: UNKNOWN
Platform: UNKNOWN
